statssc/__init__.py
statssc/statssc.py
statssc-0.0.3.dist-info/METADATA
statssc-0.0.3.dist-info/WHEEL
statssc-0.0.3.dist-info/top_level.txt
statssc-0.0.3.dist-info/RECORD
