Metadata-Version: 2.1
Name: statssc
Version: 0.0.3
Summary: This is the simplest module for quick work with files.
Home-page: https://github.com/alex-past-15/sciipy
Author: alex_past_15
Author-email: pastusenkoalex@mail.ru
Project-URL: GitHub, https://github.com/alex-past-15/sciipy
Keywords: files speedfiles
Classifier: Programming Language :: Python :: 3.11
Classifier: License :: OSI Approved :: MIT License
Classifier: Operating System :: OS Independent
Requires-Python: >=3.6
Requires-Dist: requests (>=2.25.1)
